testcontainers/mssql/__init__.py
tests/test_mssql.py
testcontainers_mssql-0.0.1rc1.dist-info/METADATA
testcontainers_mssql-0.0.1rc1.dist-info/WHEEL
testcontainers_mssql-0.0.1rc1.dist-info/top_level.txt
testcontainers_mssql-0.0.1rc1.dist-info/RECORD
